py_rpautom/__init__.py
py_rpautom/desktop_utils.py
py_rpautom/python_utils.py
py_rpautom/web_utils.py
py_rpautom-0.0.55b0.dist-info/licenses/LICENSE
tests/__init__.py
tests/conftest.py
tests/test_desktop_utils.py
py_rpautom-0.0.55b0.dist-info/METADATA
py_rpautom-0.0.55b0.dist-info/WHEEL
py_rpautom-0.0.55b0.dist-info/top_level.txt
py_rpautom-0.0.55b0.dist-info/RECORD
