Metadata-Version: 2.4
Name: py-rpautom
Version: 0.0.55b0
Summary: Conjunto de utilitários para automação de processos.
Home-page: https://aranseiki.github.io/py-rpautom/
Author: aranseiki
Author-email: allanoa@5t2tj5.onmicrosoft.com
Project-URL: Py-RPAutom, https://github.com/aranseiki/py-rpautom/
Classifier: Framework :: Robot Framework :: Library
Classifier: Operating System :: Microsoft :: Windows
Classifier: Programming Language :: Python :: 3
Classifier: Development Status :: 4 - Beta
Classifier: Topic :: Utilities
Requires-Python: >=3.9
License-File: LICENSE
Requires-Dist: openpyxl
Requires-Dist: psutil
Requires-Dist: pywinauto
Requires-Dist: pywin32
Requires-Dist: PyMuPDF
Requires-Dist: PyPDF2
Requires-Dist: Pytesseract
Requires-Dist: requests
Requires-Dist: selenium
Requires-Dist: urllib3
Requires-Dist: xlrd
Requires-Dist: requests_html
Requires-Dist: lxml_html_clean
Dynamic: author
Dynamic: author-email
Dynamic: classifier
Dynamic: description
Dynamic: description-content-type
Dynamic: home-page
Dynamic: license-file
Dynamic: project-url
Dynamic: requires-dist
Dynamic: requires-python
Dynamic: summary
